<?xml version="1.1" encoding="UTF-8" standalone="no"?>
<databaseChangeLog xmlns="http://www.liquibase.org/xml/ns/dbchangelog" xmlns:ext="http://www.liquibase.org/xml/ns/dbchangelog-ext" xmlns:pro="http://www.liquibase.org/xml/ns/pro" xmlns:xsi="http://www.w3.org/2001/XMLSchema-instance" xsi:schemaLocation="http://www.liquibase.org/xml/ns/dbchangelog-ext http://www.liquibase.org/xml/ns/dbchangelog/dbchangelog-ext.xsd http://www.liquibase.org/xml/ns/pro http://www.liquibase.org/xml/ns/pro/liquibase-pro-4.1.xsd http://www.liquibase.org/xml/ns/dbchangelog http://www.liquibase.org/xml/ns/dbchangelog/dbchangelog-4.1.xsd">
    <changeSet author="braquartdav (generated)" id="1686826678649-5">
        <createTable tableName="shunt_compensators_side1">
            <column name="equipment_deletion_entity_id" type="UUID">
                <constraints nullable="false"/>
            </column>
            <column name="selected" type="BOOLEAN"/>
            <column name="shunt_compensator_id" type="VARCHAR(255)"/>
        </createTable>
    </changeSet>
    <changeSet author="braquartdav (generated)" id="1686826678649-6">
        <createTable tableName="shunt_compensators_side2">
            <column name="equipment_deletion_entity_id" type="UUID">
                <constraints nullable="false"/>
            </column>
            <column name="selected" type="BOOLEAN"/>
            <column name="shunt_compensator_id" type="VARCHAR(255)"/>
        </createTable>
    </changeSet>
    <changeSet author="braquartdav (generated)" id="1686826678649-7">
        <addColumn tableName="equipment_deletion">
            <column defaultValueBoolean="false" name="hvdc_withlcc" type="boolean"/>
        </addColumn>
    </changeSet>
    <changeSet author="braquartdav (generated)" id="1686826678649-8">
        <addForeignKeyConstraint baseColumnNames="equipment_deletion_entity_id" baseTableName="shunt_compensators_side1" constraintName="FK709bfryl3pki0o4i6f6w3j0m0" deferrable="false" initiallyDeferred="false" referencedColumnNames="id" referencedTableName="equipment_deletion" validate="true"/>
    </changeSet>
    <changeSet author="braquartdav (generated)" id="1686826678649-9">
        <addForeignKeyConstraint baseColumnNames="equipment_deletion_entity_id" baseTableName="shunt_compensators_side2" constraintName="FKr41lr9ktup4ytt2casxs0745d" deferrable="false" initiallyDeferred="false" referencedColumnNames="id" referencedTableName="equipment_deletion" validate="true"/>
    </changeSet>
</databaseChangeLog>
